pypipegraph/__init__.py
pypipegraph/graph.py
pypipegraph/interactive.py
pypipegraph/job.py
pypipegraph/ppg_exceptions.py
pypipegraph/resource_coordinators.py
pypipegraph/util.py
pypipegraph/testing/__init__.py
pypipegraph/testing/fixtures.py
pypipegraph/utils/autotest.py
pypipegraph/utils/filter_job_from_status.py
pypipegraph/utils/invariant_diff.py
pypipegraph/utils/log_listen.py
pypipegraph-0.197.dist-info/COPYING
pypipegraph-0.197.dist-info/METADATA
pypipegraph-0.197.dist-info/WHEEL
pypipegraph-0.197.dist-info/entry_points.txt
pypipegraph-0.197.dist-info/top_level.txt
pypipegraph-0.197.dist-info/RECORD
